superml/__init__.py
superml/classifier.py
superml-0.1.0.dist-info/LICENSE
superml-0.1.0.dist-info/METADATA
superml-0.1.0.dist-info/WHEEL
superml-0.1.0.dist-info/top_level.txt
superml-0.1.0.dist-info/RECORD
