Metadata-Version: 2.1
Name: superml
Version: 0.1.0
Summary: `superml` is a shortcut to ML. A wrapper of scikit-learn, etc.
Home-page: http://github.com/wlongxiang/superml
Author: Benjamin Wang
Author-email: wlongxiang1119@gmail.com
License: MIT
Platform: UNKNOWN
